setup.py
Largeman.egg-info/PKG-INFO
Largeman.egg-info/SOURCES.txt
Largeman.egg-info/dependency_links.txt
Largeman.egg-info/top_level.txt
largeman/__init__.py
largeman/state_machine.py
largeman.egg-info/SOURCES.txt