Metadata-Version: 1.1
Name: largeman
Version: 0.1.0
Summary: A little library for making, and using state machines.
Home-page: https://github.com/sneeu/largeman
Author: John Sutherland
Author-email: john@sneeu.com
License: MIT license
Platform: UNKNOWN
Classifier: Development Status :: 4 - Beta
Classifier: Intended Audience :: Developers
Classifier: Natural Language :: English
Classifier: License :: OSI Approved :: MIT License
Classifier: Programming Language :: Python
Classifier: Programming Language :: Python :: 2.6
Classifier: Programming Language :: Python :: 2.7
Classifier: Programming Language :: Python :: 3.3
